tiler/__init__.py
tiler/_windows.py
tiler/merger.py
tiler/py.typed
tiler/tiler.py
tiler-0.6.0.dist-info/licenses/LICENSE.md
tiler-0.6.0.dist-info/METADATA
tiler-0.6.0.dist-info/WHEEL
tiler-0.6.0.dist-info/top_level.txt
tiler-0.6.0.dist-info/RECORD
