Metadata-Version: 2.4
Name: tiler
Version: 0.6.0
Summary: N-dimensional NumPy array tiling and merging with overlapping, padding and tapering
Author-email: the-lay <ilja.gubin@gmail.com>
License: MIT
Project-URL: Documentation, https://the-lay.github.io/tiler/
Project-URL: Source, https://github.com/the-lay/tiler
Project-URL: Issues, https://github.com/the-lay/tiler/issues
Classifier: Development Status :: 4 - Beta
Classifier: Intended Audience :: Developers
Classifier: Intended Audience :: Science/Research
Classifier: Topic :: Software Development :: Libraries :: Python Modules
Classifier: License :: OSI Approved :: MIT License
Classifier: Programming Language :: Python :: 3 :: Only
Requires-Python: >=3.9
License-File: LICENSE.md
Requires-Dist: numpy
Requires-Dist: tqdm
Provides-Extra: test
Requires-Dist: pytest; extra == "test"
Requires-Dist: coverage[toml]; extra == "test"
Provides-Extra: docs
Requires-Dist: pdoc==15.0.3; extra == "docs"
Provides-Extra: all
Requires-Dist: pytest; extra == "all"
Requires-Dist: coverage[toml]; extra == "all"
Requires-Dist: pdoc==15.0.3; extra == "all"
Dynamic: license-file
